tdyno/__init__.py
tdyno/a_pchs.py
tdyno/cnst.py
tdyno/dom.py
tdyno/pct.py
tdyno/plot_field_2d_in_ax_3.py
tdyno/rt2.py
tdyno/s2t.py
tdyno/sc2t.py
tdyno/sc2t_md.py
tdyno/sc_tp_t.py
tdyno/simulator.py
tdyno/mnt/__init__.py
tdyno/mnt/mnt_t_fa.py
tdyno/mnt/mnt_t_md.py
tdyno/mnt/mnt_t_md_ui.py
tdyno/mnt/mnt_t_poyn.py
tdyno/mnt/mnt_ui.py
tdyno/mnt/sig_spct.py
tdyno-0.1.7.dist-info/LICENSE
tdyno-0.1.7.dist-info/METADATA
tdyno-0.1.7.dist-info/WHEEL
tdyno-0.1.7.dist-info/top_level.txt
tdyno-0.1.7.dist-info/RECORD
