Metadata-Version: 2.1
Name: tdyno
Version: 0.1.7
Summary: FDTD with dynamic modulations in the refractive index or the gain/loss in materials.
Home-page: https://github.com/alexysong/tdyno
Author: Alex Y. Song
Author-email: song.alexy@gmail.com
License: UNKNOWN
Keywords: fdtd,dynamic modulation
Platform: UNKNOWN
Classifier: Programming Language :: Python :: 2.7
Classifier: Programming Language :: Python :: 3
Classifier: Topic :: Scientific/Engineering
Classifier: License :: OSI Approved :: GNU Affero General Public License v3 or later (AGPLv3+)
Requires-Dist: numpy (>=1.11.3)
Requires-Dist: scipy (>=0.19.0)
Requires-Dist: matplotlib (>=2.0.0)
